{
  "project_info": {
    "project_number": "249172404436",
    "firebase_url": "https://shop-1c3e4.firebaseio.com",
    "project_id": "shop-1c3e4",
    "storage_bucket": "shop-1c3e4.appspot.com"
  },
  "client": [
    {
      "client_info": {
        "mobilesdk_app_id": "1:249172404436:android:60ac71cb1895cd2e70f341",
        "android_client_info": {
          "package_name": "com.sayedvip.shop"
        }
      },
      "oauth_client": [
        {
          "client_id": "249172404436-vhvi0vvn6pc3913sntov3vehhken8r62.apps.googleusercontent.com",
          "client_type": 1,
          "android_info": {
            "package_name": "com.sayedvip.shop",
            "certificate_hash": "efa9c43d3331bf47e122ee0393cb8a192b3cd366"
          }
        },
        {
          "client_id": "249172404436-ufu00vdft3f3vfv7ae137j9qabgpl44t.apps.googleusercontent.com",
          "client_type": 3
        }
      ],
      "api_key": [
        {
          "current_key": "AIzaSyCKxRgcea7R20LIHRZwc1Vn7Y-cbRhquRk"
        }
      ],
      "services": {
        "appinvite_service": {
          "other_platform_oauth_client": [
            {
              "client_id": "249172404436-ufu00vdft3f3vfv7ae137j9qabgpl44t.apps.googleusercontent.com",
              "client_type": 3
            }
          ]
        }
      }
    }
  ],
  "configuration_version": "1"
}